render_cli/__init__.py
render_cli/console.py
render_cli/output/services_output.py
render_cli/render_services.py
render_cli-0.1.1.dist-info/entry_points.txt
render_cli-0.1.1.dist-info/LICENSE
render_cli-0.1.1.dist-info/WHEEL
render_cli-0.1.1.dist-info/METADATA
render_cli-0.1.1.dist-info/RECORD
