Metadata-Version: 2.1
Name: render-cli
Version: 0.1.1
Summary: Render CLI - a command line interface for use with Render https://render.com/
Home-page: https://github.com/mnapoleon/render-cli
License: MIT
Keywords: render,render-cli,python
Author: michaelnapoloen
Author-email: michael.napoleon@gmail.com
Requires-Python: >=3.9,<4.0
Classifier: License :: OSI Approved :: MIT License
Classifier: Programming Language :: Python :: 3
Classifier: Programming Language :: Python :: 3.9
Classifier: Programming Language :: Python :: 3.10
Requires-Dist: click (>=8.1.3,<9.0.0)
Requires-Dist: nox (>=2022.8.7,<2023.0.0)
Requires-Dist: requests (>=2.28.1,<3.0.0)
Requires-Dist: rich (>=12.5.1,<13.0.0)
Project-URL: Repository, https://github.com/mnapoleon/render-cli
